{
	"info": {
		"_postman_id": "820eb942-292c-42a3-af76-7f46494cf532",
		"name": "Aula24 - Spotif4",
		"schema": "https://schema.getpostman.com/json/collection/v2.1.0/collection.json"
	},
	"item": [
		{
			"name": "1 - Playlist Rock",
			"request": {
				"method": "POST",
				"header": [
					{
						"key": "Content-Type",
						"name": "Content-Type",
						"value": "application/json",
						"type": "text"
					},
					{
						"key": "auth",
						"value": "7a175c559832cbe6db0112d56e63da03",
						"type": "text"
					}
				],
				"body": {
					"mode": "raw",
					"raw": "{\r\n    \"name\": \"ClassicRock\" \r\n}",
					"options": {
						"raw": {
							"language": "json"
						}
					}
				},
				"url": {
					"raw": "https://us-central1-spotif4.cloudfunctions.net/api/playlists/createPlaylist",
					"protocol": "https",
					"host": [
						"us-central1-spotif4",
						"cloudfunctions",
						"net"
					],
					"path": [
						"api",
						"playlists",
						"createPlaylist"
					]
				}
			},
			"response": []
		},
		{
			"name": "1.2 - Playlist Jazz",
			"request": {
				"method": "POST",
				"header": [
					{
						"key": "Content-Type",
						"name": "Content-Type",
						"value": "application/json",
						"type": "text"
					},
					{
						"key": "auth",
						"value": "7a175c559832cbe6db0112d56e63da03",
						"type": "text"
					}
				],
				"body": {
					"mode": "raw",
					"raw": "{\r\n    \"name\": \"Jazz\" \r\n}",
					"options": {
						"raw": {
							"language": "json"
						}
					}
				},
				"url": {
					"raw": "https://us-central1-spotif4.cloudfunctions.net/api/playlists/createPlaylist",
					"protocol": "https",
					"host": [
						"us-central1-spotif4",
						"cloudfunctions",
						"net"
					],
					"path": [
						"api",
						"playlists",
						"createPlaylist"
					]
				}
			},
			"response": []
		},
		{
			"name": "1.3 - Playlist 50s",
			"request": {
				"method": "POST",
				"header": [
					{
						"key": "Content-Type",
						"name": "Content-Type",
						"value": "application/json",
						"type": "text"
					},
					{
						"key": "auth",
						"value": "7a175c559832cbe6db0112d56e63da03",
						"type": "text"
					}
				],
				"body": {
					"mode": "raw",
					"raw": "{\r\n    \"name\": \"50s\" \r\n}",
					"options": {
						"raw": {
							"language": "json"
						}
					}
				},
				"url": {
					"raw": "https://us-central1-spotif4.cloudfunctions.net/api/playlists/createPlaylist",
					"protocol": "https",
					"host": [
						"us-central1-spotif4",
						"cloudfunctions",
						"net"
					],
					"path": [
						"api",
						"playlists",
						"createPlaylist"
					]
				}
			},
			"response": []
		},
		{
			"name": "2 - Vendo todas as playlists",
			"request": {
				"method": "GET",
				"header": [
					{
						"key": "auth",
						"value": "7a175c559832cbe6db0112d56e63da03",
						"type": "text"
					}
				],
				"url": {
					"raw": "https://us-central1-spotif4.cloudfunctions.net/api/playlists/getAllPlaylists",
					"protocol": "https",
					"host": [
						"us-central1-spotif4",
						"cloudfunctions",
						"net"
					],
					"path": [
						"api",
						"playlists",
						"getAllPlaylists"
					],
					"query": [
						{
							"key": "",
							"value": "",
							"disabled": true
						}
					]
				}
			},
			"response": []
		},
		{
			"name": "3 - Add Music Playlist Rock",
			"request": {
				"method": "PUT",
				"header": [
					{
						"key": "Content-Type",
						"name": "Content-Type",
						"value": "application/json",
						"type": "text"
					},
					{
						"key": "auth",
						"value": "7a175c559832cbe6db0112d56e63da03",
						"type": "text"
					}
				],
				"body": {
					"mode": "raw",
					"raw": "{\r\n\t\"playlistId\": \"bffdadb9-bf5a-4b15-94b1-07aa635b7b96\",\r\n\t\"music\": {\r\n\t\t\"name\": \"Pour Some Sugar on Me\",\r\n\t\t\"artist\": \"Def Leppard\"\r\n\t}\r\n}",
					"options": {
						"raw": {
							"language": "json"
						}
					}
				},
				"url": {
					"raw": "https://us-central1-spotif4.cloudfunctions.net/api/playlists/addMusicToPlaylist",
					"protocol": "https",
					"host": [
						"us-central1-spotif4",
						"cloudfunctions",
						"net"
					],
					"path": [
						"api",
						"playlists",
						"addMusicToPlaylist"
					]
				}
			},
			"response": []
		},
		{
			"name": "3 - Add Music Playlist Rock + 1",
			"request": {
				"method": "PUT",
				"header": [
					{
						"key": "Content-Type",
						"name": "Content-Type",
						"value": "application/json",
						"type": "text"
					},
					{
						"key": "auth",
						"value": "7a175c559832cbe6db0112d56e63da03",
						"type": "text"
					}
				],
				"body": {
					"mode": "raw",
					"raw": "{\r\n\t\"playlistId\": \"bffdadb9-bf5a-4b15-94b1-07aa635b7b96\",\r\n\t\"music\": {\r\n\t\t\"name\": \"Carry On Wayward Son\",\r\n\t\t\"artist\": \"Kansas\"\r\n\t}\r\n}",
					"options": {
						"raw": {
							"language": "json"
						}
					}
				},
				"url": {
					"raw": "https://us-central1-spotif4.cloudfunctions.net/api/playlists/addMusicToPlaylist",
					"protocol": "https",
					"host": [
						"us-central1-spotif4",
						"cloudfunctions",
						"net"
					],
					"path": [
						"api",
						"playlists",
						"addMusicToPlaylist"
					]
				}
			},
			"response": []
		},
		{
			"name": "3 - Add Music Playlist Jazz",
			"request": {
				"method": "PUT",
				"header": [
					{
						"key": "Content-Type",
						"name": "Content-Type",
						"value": "application/json",
						"type": "text"
					},
					{
						"key": "auth",
						"value": "7a175c559832cbe6db0112d56e63da03",
						"type": "text"
					}
				],
				"body": {
					"mode": "raw",
					"raw": "{\r\n\t\"playlistId\": \"aadf4d7d-3136-47da-8253-1c87a01e1c5f\",\r\n\t\"music\": {\r\n\t\t\"name\": \"St James Infirmary\",\r\n\t\t\"artist\": \"Hugh Laurie\"\r\n\t}\r\n}",
					"options": {
						"raw": {
							"language": "json"
						}
					}
				},
				"url": {
					"raw": "https://us-central1-spotif4.cloudfunctions.net/api/playlists/addMusicToPlaylist",
					"protocol": "https",
					"host": [
						"us-central1-spotif4",
						"cloudfunctions",
						"net"
					],
					"path": [
						"api",
						"playlists",
						"addMusicToPlaylist"
					]
				}
			},
			"response": []
		},
		{
			"name": "3 - Add Music Playlist Jazz + 1",
			"request": {
				"method": "PUT",
				"header": [
					{
						"key": "Content-Type",
						"name": "Content-Type",
						"value": "application/json",
						"type": "text"
					},
					{
						"key": "auth",
						"value": "7a175c559832cbe6db0112d56e63da03",
						"type": "text"
					}
				],
				"body": {
					"mode": "raw",
					"raw": "{\r\n\t\"playlistId\": \"aadf4d7d-3136-47da-8253-1c87a01e1c5f\",\r\n\t\"music\": {\r\n\t\t\"name\": \"Ou Est Ma Tete\",\r\n\t\t\"artist\": \"Pink Martini\"\r\n\t}\r\n}",
					"options": {
						"raw": {
							"language": "json"
						}
					}
				},
				"url": {
					"raw": "https://us-central1-spotif4.cloudfunctions.net/api/playlists/addMusicToPlaylist",
					"protocol": "https",
					"host": [
						"us-central1-spotif4",
						"cloudfunctions",
						"net"
					],
					"path": [
						"api",
						"playlists",
						"addMusicToPlaylist"
					]
				}
			},
			"response": []
		},
		{
			"name": "3 - Add Music Playlist 50s",
			"request": {
				"method": "PUT",
				"header": [
					{
						"key": "Content-Type",
						"name": "Content-Type",
						"value": "application/json",
						"type": "text"
					},
					{
						"key": "auth",
						"value": "7a175c559832cbe6db0112d56e63da03",
						"type": "text"
					}
				],
				"body": {
					"mode": "raw",
					"raw": "{\r\n\t\"playlistId\": \"743a20d1-6186-4045-8ba7-bf5572a69c59\",\r\n\t\"music\": {\r\n\t\t\"name\": \"Music is Better Than Words\",\r\n\t\t\"artist\": \"Seth McFarlane\"\r\n\t}\r\n}",
					"options": {
						"raw": {
							"language": "json"
						}
					}
				},
				"url": {
					"raw": "https://us-central1-spotif4.cloudfunctions.net/api/playlists/addMusicToPlaylist",
					"protocol": "https",
					"host": [
						"us-central1-spotif4",
						"cloudfunctions",
						"net"
					],
					"path": [
						"api",
						"playlists",
						"addMusicToPlaylist"
					]
				}
			},
			"response": []
		},
		{
			"name": "3 - Add Music Playlist 50s + 1",
			"request": {
				"method": "PUT",
				"header": [
					{
						"key": "Content-Type",
						"name": "Content-Type",
						"value": "application/json",
						"type": "text"
					},
					{
						"key": "auth",
						"value": "7a175c559832cbe6db0112d56e63da03",
						"type": "text"
					}
				],
				"body": {
					"mode": "raw",
					"raw": "{\r\n\t\"playlistId\": \"743a20d1-6186-4045-8ba7-bf5572a69c59\",\r\n\t\"music\": {\r\n\t\t\"name\": \"Well Did You Evah\",\r\n\t\t\"artist\": \"Frank Sinatra\"\r\n\t}\r\n}",
					"options": {
						"raw": {
							"language": "json"
						}
					}
				},
				"url": {
					"raw": "https://us-central1-spotif4.cloudfunctions.net/api/playlists/addMusicToPlaylist",
					"protocol": "https",
					"host": [
						"us-central1-spotif4",
						"cloudfunctions",
						"net"
					],
					"path": [
						"api",
						"playlists",
						"addMusicToPlaylist"
					]
				}
			},
			"response": []
		},
		{
			"name": "4 - Check All Playlists Id",
			"request": {
				"method": "GET",
				"header": [
					{
						"key": "auth",
						"value": "7a175c559832cbe6db0112d56e63da03",
						"type": "text"
					}
				],
				"url": {
					"raw": "https://us-central1-spotif4.cloudfunctions.net/api/playlists/getAllPlaylists",
					"protocol": "https",
					"host": [
						"us-central1-spotif4",
						"cloudfunctions",
						"net"
					],
					"path": [
						"api",
						"playlists",
						"getAllPlaylists"
					]
				}
			},
			"response": []
		},
		{
			"name": "4.1 - Check All Playlists Music Rock",
			"request": {
				"method": "GET",
				"header": [
					{
						"key": "auth",
						"value": "7a175c559832cbe6db0112d56e63da03",
						"type": "text"
					}
				],
				"url": {
					"raw": "https://us-central1-spotif4.cloudfunctions.net/api/playlists/getPlaylistMusics/bffdadb9-bf5a-4b15-94b1-07aa635b7b96",
					"protocol": "https",
					"host": [
						"us-central1-spotif4",
						"cloudfunctions",
						"net"
					],
					"path": [
						"api",
						"playlists",
						"getPlaylistMusics",
						"bffdadb9-bf5a-4b15-94b1-07aa635b7b96"
					]
				}
			},
			"response": []
		},
		{
			"name": "4.1 - Check All Playlists Music Jazz",
			"request": {
				"method": "GET",
				"header": [
					{
						"key": "auth",
						"value": "7a175c559832cbe6db0112d56e63da03",
						"type": "text"
					}
				],
				"url": {
					"raw": "https://us-central1-spotif4.cloudfunctions.net/api/playlists/getPlaylistMusics/aadf4d7d-3136-47da-8253-1c87a01e1c5f",
					"protocol": "https",
					"host": [
						"us-central1-spotif4",
						"cloudfunctions",
						"net"
					],
					"path": [
						"api",
						"playlists",
						"getPlaylistMusics",
						"aadf4d7d-3136-47da-8253-1c87a01e1c5f"
					]
				}
			},
			"response": []
		},
		{
			"name": "4.1 - Check All Playlists Music 50s",
			"request": {
				"method": "GET",
				"header": [
					{
						"key": "auth",
						"value": "7a175c559832cbe6db0112d56e63da03",
						"type": "text"
					}
				],
				"url": {
					"raw": "https://us-central1-spotif4.cloudfunctions.net/api/playlists/getPlaylistMusics/743a20d1-6186-4045-8ba7-bf5572a69c59",
					"protocol": "https",
					"host": [
						"us-central1-spotif4",
						"cloudfunctions",
						"net"
					],
					"path": [
						"api",
						"playlists",
						"getPlaylistMusics",
						"743a20d1-6186-4045-8ba7-bf5572a69c59"
					]
				}
			},
			"response": []
		},
		{
			"name": "5 - Check All Playlists Music",
			"request": {
				"method": "GET",
				"header": [
					{
						"key": "auth",
						"value": "7a175c559832cbe6db0112d56e63da03",
						"type": "text"
					}
				],
				"url": {
					"raw": "https://us-central1-spotif4.cloudfunctions.net/api/playlists/getAllPlaylists",
					"protocol": "https",
					"host": [
						"us-central1-spotif4",
						"cloudfunctions",
						"net"
					],
					"path": [
						"api",
						"playlists",
						"getAllPlaylists"
					]
				}
			},
			"response": []
		},
		{
			"name": "5.1 - Add Music Playlist Rock",
			"request": {
				"method": "PUT",
				"header": [
					{
						"key": "auth",
						"value": "7a175c559832cbe6db0112d56e63da03",
						"type": "text"
					},
					{
						"key": "Content-Type",
						"name": "Content-Type",
						"value": "application/json",
						"type": "text"
					}
				],
				"body": {
					"mode": "raw",
					"raw": "{\r\n\t\"playlistId\": \"bffdadb9-bf5a-4b15-94b1-07aa635b7b96\",\r\n\t\"music\": {\r\n\t\t\"name\": \"Summer of 69\",\r\n\t\t\"artist\": \"Bryan Adams\"\r\n\t}\r\n}",
					"options": {
						"raw": {
							"language": "json"
						}
					}
				},
				"url": {
					"raw": "https://us-central1-spotif4.cloudfunctions.net/api/playlists/addMusicToPlaylist",
					"protocol": "https",
					"host": [
						"us-central1-spotif4",
						"cloudfunctions",
						"net"
					],
					"path": [
						"api",
						"playlists",
						"addMusicToPlaylist"
					]
				}
			},
			"response": []
		},
		{
			"name": "5.1 - Add Music Playlist Rock + 1",
			"request": {
				"method": "PUT",
				"header": [
					{
						"key": "auth",
						"value": "7a175c559832cbe6db0112d56e63da03",
						"type": "text"
					},
					{
						"key": "Content-Type",
						"name": "Content-Type",
						"value": "application/json",
						"type": "text"
					}
				],
				"body": {
					"mode": "raw",
					"raw": "{\r\n\t\"playlistId\": \"bffdadb9-bf5a-4b15-94b1-07aa635b7b96\",\r\n\t\"music\": {\r\n\t\t\"name\": \"Lay Dowm Sally\",\r\n\t\t\"artist\": \"Eric Clapton\"\r\n\t}\r\n}",
					"options": {
						"raw": {
							"language": "json"
						}
					}
				},
				"url": {
					"raw": "https://us-central1-spotif4.cloudfunctions.net/api/playlists/addMusicToPlaylist",
					"protocol": "https",
					"host": [
						"us-central1-spotif4",
						"cloudfunctions",
						"net"
					],
					"path": [
						"api",
						"playlists",
						"addMusicToPlaylist"
					]
				}
			},
			"response": []
		},
		{
			"name": "6 - Check Playlist Music",
			"request": {
				"method": "GET",
				"header": [
					{
						"key": "auth",
						"value": "7a175c559832cbe6db0112d56e63da03",
						"type": "text"
					}
				],
				"url": {
					"raw": "https://us-central1-spotif4.cloudfunctions.net/api/playlists/getPlaylistMusics/bffdadb9-bf5a-4b15-94b1-07aa635b7b96",
					"protocol": "https",
					"host": [
						"us-central1-spotif4",
						"cloudfunctions",
						"net"
					],
					"path": [
						"api",
						"playlists",
						"getPlaylistMusics",
						"bffdadb9-bf5a-4b15-94b1-07aa635b7b96"
					]
				}
			},
			"response": []
		},
		{
			"name": "7 - Add Music to Playlist",
			"request": {
				"method": "PUT",
				"header": [
					{
						"key": "auth",
						"value": "7a175c559832cbe6db0112d56e63da03",
						"type": "text"
					},
					{
						"key": "Content-Type",
						"name": "Content-Type",
						"value": "application/json",
						"type": "text"
					}
				],
				"body": {
					"mode": "raw",
					"raw": "{\r\n\t\"playlistId\": \"bffdadb9-bf5a-4b15-94b1-07aa635b7b96\",\r\n\t\"music\": {\r\n\t\t\"name\": \"Gimme All Your Lovin\",\r\n\t\t\"artist\": \"ZZ Top\"\r\n\t}\r\n}",
					"options": {
						"raw": {
							"language": "json"
						}
					}
				},
				"url": {
					"raw": "https://us-central1-spotif4.cloudfunctions.net/api/playlists/addMusicToPlaylist",
					"protocol": "https",
					"host": [
						"us-central1-spotif4",
						"cloudfunctions",
						"net"
					],
					"path": [
						"api",
						"playlists",
						"addMusicToPlaylist"
					]
				}
			},
			"response": []
		},
		{
			"name": "8 - Check Playlist Music",
			"request": {
				"method": "GET",
				"header": [
					{
						"key": "auth",
						"value": "7a175c559832cbe6db0112d56e63da03",
						"type": "text"
					}
				],
				"url": {
					"raw": "https://us-central1-spotif4.cloudfunctions.net/api/playlists/getPlaylistMusics/bffdadb9-bf5a-4b15-94b1-07aa635b7b96",
					"protocol": "https",
					"host": [
						"us-central1-spotif4",
						"cloudfunctions",
						"net"
					],
					"path": [
						"api",
						"playlists",
						"getPlaylistMusics",
						"bffdadb9-bf5a-4b15-94b1-07aa635b7b96"
					]
				}
			},
			"response": []
		},
		{
			"name": "9 - Delete Music",
			"request": {
				"method": "DELETE",
				"header": [
					{
						"key": "auth",
						"value": "7a175c559832cbe6db0112d56e63da03",
						"type": "text"
					}
				],
				"url": {
					"raw": "https://us-central1-spotif4.cloudfunctions.net/api/playlists/removeMusicFromPlaylist?playlistId=bffdadb9-bf5a-4b15-94b1-07aa635b7b96&musicId=49e655d3-f5b6-403c-882f-c3185bc15968",
					"protocol": "https",
					"host": [
						"us-central1-spotif4",
						"cloudfunctions",
						"net"
					],
					"path": [
						"api",
						"playlists",
						"removeMusicFromPlaylist"
					],
					"query": [
						{
							"key": "playlistId",
							"value": "bffdadb9-bf5a-4b15-94b1-07aa635b7b96"
						},
						{
							"key": "musicId",
							"value": "49e655d3-f5b6-403c-882f-c3185bc15968"
						}
					]
				}
			},
			"response": []
		},
		{
			"name": "10 - Check Playlist Music",
			"request": {
				"method": "GET",
				"header": [
					{
						"key": "auth",
						"value": "7a175c559832cbe6db0112d56e63da03",
						"type": "text"
					}
				],
				"url": {
					"raw": "https://us-central1-spotif4.cloudfunctions.net/api/playlists/getPlaylistMusics/bffdadb9-bf5a-4b15-94b1-07aa635b7b96",
					"protocol": "https",
					"host": [
						"us-central1-spotif4",
						"cloudfunctions",
						"net"
					],
					"path": [
						"api",
						"playlists",
						"getPlaylistMusics",
						"bffdadb9-bf5a-4b15-94b1-07aa635b7b96"
					]
				}
			},
			"response": []
		},
		{
			"name": "10.a",
			"request": {
				"method": "DELETE",
				"header": [
					{
						"key": "auth",
						"value": "7a175c559832cbe6db0112d56e63da03",
						"type": "text"
					}
				],
				"url": {
					"raw": "https://us-central1-spotif4.cloudfunctions.net/api/playlists/deletePlaylist?playlistId=743a20d1-6186-4045-8ba7-bf5572a69c59\n",
					"protocol": "https",
					"host": [
						"us-central1-spotif4",
						"cloudfunctions",
						"net"
					],
					"path": [
						"api",
						"playlists",
						"deletePlaylist"
					],
					"query": [
						{
							"key": "playlistId",
							"value": "743a20d1-6186-4045-8ba7-bf5572a69c59\n"
						}
					]
				}
			},
			"response": []
		},
		{
			"name": "10.b",
			"protocolProfileBehavior": {
				"disableBodyPruning": true
			},
			"request": {
				"method": "GET",
				"header": [
					{
						"key": "auth",
						"value": "7a175c559832cbe6db0112d56e63da03",
						"type": "text"
					},
					{
						"key": "",
						"name": "Content-Type",
						"value": "",
						"type": "text",
						"disabled": true
					},
					{
						"key": "Content-Type",
						"value": "",
						"disabled": true
					}
				],
				"body": {
					"mode": "raw",
					"raw": "",
					"options": {
						"raw": {
							"language": "json"
						}
					}
				},
				"url": {
					"raw": "https://us-central1-spotif4.cloudfunctions.net/api/playlists/getAllPlaylists",
					"protocol": "https",
					"host": [
						"us-central1-spotif4",
						"cloudfunctions",
						"net"
					],
					"path": [
						"api",
						"playlists",
						"getAllPlaylists"
					]
				}
			},
			"response": []
		},
		{
			"name": "10.c",
			"protocolProfileBehavior": {
				"disableBodyPruning": true
			},
			"request": {
				"method": "GET",
				"header": [
					{
						"key": "auth",
						"value": "7a175c559832cbe6db0112d56e63da03",
						"type": "text"
					},
					{
						"key": "",
						"name": "Content-Type",
						"value": "",
						"type": "text",
						"disabled": true
					},
					{
						"key": "Content-Type",
						"value": "",
						"disabled": true
					}
				],
				"body": {
					"mode": "raw",
					"raw": "",
					"options": {
						"raw": {
							"language": "json"
						}
					}
				},
				"url": {
					"raw": "https://us-central1-spotif4.cloudfunctions.net/api/playlists/getPlaylistMusics/d0e481f8-fc61-4628-854a-f035cd06f411",
					"protocol": "https",
					"host": [
						"us-central1-spotif4",
						"cloudfunctions",
						"net"
					],
					"path": [
						"api",
						"playlists",
						"getPlaylistMusics",
						"d0e481f8-fc61-4628-854a-f035cd06f411"
					]
				}
			},
			"response": []
		},
		{
			"name": "10.d",
			"request": {
				"method": "DELETE",
				"header": [
					{
						"key": "auth",
						"value": "7a175c559832cbe6db0112d56e63da03",
						"type": "text"
					}
				],
				"url": {
					"raw": "https://us-central1-spotif4.cloudfunctions.net/api/playlists/removeMusicFromPlaylist?playlistId=d0e481f8-fc61-4628-854a-f035cd06f411&musicId=46125626-8368-4632-81da-9316477234dc",
					"protocol": "https",
					"host": [
						"us-central1-spotif4",
						"cloudfunctions",
						"net"
					],
					"path": [
						"api",
						"playlists",
						"removeMusicFromPlaylist"
					],
					"query": [
						{
							"key": "playlistId",
							"value": "d0e481f8-fc61-4628-854a-f035cd06f411"
						},
						{
							"key": "musicId",
							"value": "46125626-8368-4632-81da-9316477234dc"
						}
					]
				}
			},
			"response": []
		},
		{
			"name": "10.e",
			"protocolProfileBehavior": {
				"disableBodyPruning": true
			},
			"request": {
				"method": "GET",
				"header": [
					{
						"key": "auth",
						"value": "7a175c559832cbe6db0112d56e63da03",
						"type": "text"
					},
					{
						"key": "Content-Type",
						"name": "Content-Type",
						"value": "application/json",
						"type": "text",
						"disabled": true
					}
				],
				"body": {
					"mode": "raw",
					"raw": "",
					"options": {
						"raw": {
							"language": "json"
						}
					}
				},
				"url": {
					"raw": "https://us-central1-spotif4.cloudfunctions.net/api/playlists/getPlaylistMusics/12b517ed-6d73-433e-8926-9ce300d7f1ce",
					"protocol": "https",
					"host": [
						"us-central1-spotif4",
						"cloudfunctions",
						"net"
					],
					"path": [
						"api",
						"playlists",
						"getPlaylistMusics",
						"12b517ed-6d73-433e-8926-9ce300d7f1ce"
					]
				}
			},
			"response": []
		}
	],
	"protocolProfileBehavior": {}
}